




[{"content":"","date":"1年1月1日","externalUrl":null,"permalink":"/zh/","section":"","summary":"","title":"","type":"page"},{"content":"","date":"1年1月1日","externalUrl":null,"permalink":"/zh/authors/","section":"Authors","summary":"","title":"Authors","type":"authors"},{"content":"","date":"1年1月1日","externalUrl":null,"permalink":"/zh/categories/","section":"Categories","summary":"","title":"Categories","type":"categories"},{"content":"","date":"1年1月1日","externalUrl":null,"permalink":"/zh/series/","section":"Series","summary":"","title":"Series","type":"series"},{"content":"","date":"1年1月1日","externalUrl":null,"permalink":"/zh/tags/","section":"Tags","summary":"","title":"Tags","type":"tags"}]